{
  "Id": 0,
  "Location": [
    {
      "MapName": "Forest",
      "Position": [
          2,
          43
        ]
    },
    {
      "MapName": "Forest",
      "Position": [
          2,
          44
        ]
    },
    {
      "MapName": "Forest",
      "Position": [
          2,
          45
        ]
    }
  ],
  "EventName": "Animation R1S4TT | Conversation Mori_noa",
  "TriggerType": 0,
  "FlagCondition": {
    "Flag": [
      [
      "MakeibeBattleFinished",
      true
      ],
      [
        "Makeibe",
        false
      ]
    ],
    "NextFlag": [
      [
      "Makeibe",
      true
      ]
    ]
  }
}